foma_wrapper/__init__.py
foma_wrapper/foma_wrapper.py
foma_wrapper/bin/linux32/i386/CHANGELOG
foma_wrapper/bin/linux32/i386/COPYING
foma_wrapper/bin/linux32/i386/README
foma_wrapper/bin/linux32/i386/README.cmatrix
foma_wrapper/bin/linux32/i386/README.symbols
foma_wrapper/bin/linux32/i386/cgflookup
foma_wrapper/bin/linux32/i386/flookup
foma_wrapper/bin/linux32/i386/foma
foma_wrapper/bin/linux32/i386/libfoma.a
foma_wrapper/bin/linux32/i386/libfoma.so.0.9.18
foma_wrapper/bin/linux32/i386/include/fomalib.h
foma_wrapper/bin/linux32/i386/include/fomalibconf.h
foma_wrapper/bin/linux64/linux-x86_64/CHANGELOG
foma_wrapper/bin/linux64/linux-x86_64/COPYING
foma_wrapper/bin/linux64/linux-x86_64/README
foma_wrapper/bin/linux64/linux-x86_64/README.cmatrix
foma_wrapper/bin/linux64/linux-x86_64/README.symbols
foma_wrapper/bin/linux64/linux-x86_64/cgflookup
foma_wrapper/bin/linux64/linux-x86_64/flookup
foma_wrapper/bin/linux64/linux-x86_64/foma
foma_wrapper/bin/linux64/linux-x86_64/libfoma.a
foma_wrapper/bin/linux64/linux-x86_64/libfoma.so.0.9.18
foma_wrapper/bin/linux64/linux-x86_64/include/fomalib.h
foma_wrapper/bin/linux64/linux-x86_64/include/fomalibconf.h
foma_wrapper/bin/windows/win32/CHANGELOG
foma_wrapper/bin/windows/win32/COPYING
foma_wrapper/bin/windows/win32/README
foma_wrapper/bin/windows/win32/cgflookup.exe
foma_wrapper/bin/windows/win32/cygncurses7.dll
foma_wrapper/bin/windows/win32/cygreadline7.dll
foma_wrapper/bin/windows/win32/cygwin1.dll
foma_wrapper/bin/windows/win32/flookup.exe
foma_wrapper/bin/windows/win32/foma.exe
foma_wrapper/bin/windows/win32/MinGW_version/foma.exe
foma_wrapper-1.0a1.dist-info/METADATA
foma_wrapper-1.0a1.dist-info/WHEEL
foma_wrapper-1.0a1.dist-info/top_level.txt
foma_wrapper-1.0a1.dist-info/RECORD
