Metadata-Version: 2.1
Name: foma-wrapper
Version: 1.0a1
Summary: A foma wrapper with its executable
